[{"name":"Agent K.K.","link":"https:\/\/animalcrossing.fandom.com\/wiki\/Agent_K.K.","request":false},{"name":"Aloha K.K.","link":"https:\/\/animalcrossing.fandom.com\/wiki\/Aloha_K.K.","request":false},{"name":"Animal City","link":"https:\/\/animalcrossing.fandom.com\/wiki\/Animal_City","request":true},{"name":"Bubblegum K.K.","link":"https:\/\/animalcrossing.fandom.com\/wiki\/Bubblegum_K.K.","request":false},{"name":"Caf\u00e9 K.K.","link":"https:\/\/animalcrossing.fandom.com\/wiki\/Caf%C3%A9_K.K.","request":false},{"name":"Comrade K.K.","link":"https:\/\/animalcrossing.fandom.com\/wiki\/Comrade_K.K.","request":false},{"name":"DJ K.K.","link":"https:\/\/animalcrossing.fandom.com\/wiki\/DJ_K.K._(song)","request":false},{"name":"Drivin'","link":"https:\/\/animalcrossing.fandom.com\/wiki\/Drivin%27","request":true},{"name":"Farewell","link":"https:\/\/animalcrossing.fandom.com\/wiki\/Farewell","request":true},{"name":"Forest Life","link":"https:\/\/animalcrossing.fandom.com\/wiki\/Forest_Life","request":false},{"name":"Go K.K. Rider","link":"https:\/\/animalcrossing.fandom.com\/wiki\/Go_K.K._Rider","request":false},{"name":"Hypno K.K.","link":"https:\/\/animalcrossing.fandom.com\/wiki\/Hypno_K.K.","request":false},{"name":"I Love You","link":"https:\/\/animalcrossing.fandom.com\/wiki\/I_Love_You","request":false},{"name":"Imperial K.K.","link":"https:\/\/animalcrossing.fandom.com\/wiki\/Imperial_K.K.","request":false},{"name":"K.K. Adventure","link":"https:\/\/animalcrossing.fandom.com\/wiki\/K.K._Adventure","request":false},{"name":"K.K. Aria","link":"https:\/\/animalcrossing.fandom.com\/wiki\/K.K._Aria","request":false},{"name":"K.K. Ballad","link":"https:\/\/animalcrossing.fandom.com\/wiki\/K.K._Ballad","request":false},{"name":"K.K. Bazaar","link":"https:\/\/animalcrossing.fandom.com\/wiki\/K.K._Bazaar","request":false},{"name":"K.K. Birthday","link":"https:\/\/animalcrossing.fandom.com\/wiki\/K.K._Birthday","request":false},{"name":"K.K. Blues","link":"https:\/\/animalcrossing.fandom.com\/wiki\/K.K._Blues","request":false},{"name":"K.K. Bossa","link":"https:\/\/animalcrossing.fandom.com\/wiki\/K.K._Bossa","request":false},{"name":"K.K. Calypso","link":"https:\/\/animalcrossing.fandom.com\/wiki\/K.K._Calypso","request":false},{"name":"K.K. Casbah","link":"https:\/\/animalcrossing.fandom.com\/wiki\/K.K._Casbah","request":false},{"name":"K.K. Chorale","link":"https:\/\/animalcrossing.fandom.com\/wiki\/K.K._Chorale","request":false},{"name":"K.K. Condor","link":"https:\/\/animalcrossing.fandom.com\/wiki\/K.K._Condor","request":false},{"name":"K.K. Country","link":"https:\/\/animalcrossing.fandom.com\/wiki\/K.K._Country","request":false},{"name":"K.K. Cruisin'","link":"https:\/\/animalcrossing.fandom.com\/wiki\/K.K._Cruisin%27","request":false},{"name":"K.K. D&B","link":"https:\/\/animalcrossing.fandom.com\/wiki\/K.K._D%26B","request":false},{"name":"K.K. Dirge","link":"https:\/\/animalcrossing.fandom.com\/wiki\/K.K._Dirge","request":false},{"name":"K.K. Disco","link":"https:\/\/animalcrossing.fandom.com\/wiki\/K.K._Disco","request":false},{"name":"K.K. Dixie","link":"https:\/\/animalcrossing.fandom.com\/wiki\/K.K._Dixie","request":false},{"name":"K.K. \u00c9tude","link":"https:\/\/animalcrossing.fandom.com\/wiki\/K.K._%C3%89tude","request":false},{"name":"K.K. Faire","link":"https:\/\/animalcrossing.fandom.com\/wiki\/K.K._Faire","request":false},{"name":"K.K. Flamenco","link":"https:\/\/animalcrossing.fandom.com\/wiki\/K.K._Flamenco","request":false},{"name":"K.K. Folk","link":"https:\/\/animalcrossing.fandom.com\/wiki\/K.K._Folk","request":false},{"name":"K.K. Fusion","link":"https:\/\/animalcrossing.fandom.com\/wiki\/K.K._Fusion","request":false},{"name":"K.K. Groove","link":"https:\/\/animalcrossing.fandom.com\/wiki\/K.K._Groove","request":false},{"name":"K.K. Gumbo","link":"https:\/\/animalcrossing.fandom.com\/wiki\/K.K._Gumbo","request":false},{"name":"K.K. House","link":"https:\/\/animalcrossing.fandom.com\/wiki\/K.K._House","request":false},{"name":"K.K. Island","link":"https:\/\/animalcrossing.fandom.com\/wiki\/K.K._Island","request":false},{"name":"K.K. Jazz","link":"https:\/\/animalcrossing.fandom.com\/wiki\/K.K._Jazz","request":false},{"name":"K.K. Jongara","link":"https:\/\/animalcrossing.fandom.com\/wiki\/K.K._Jongara","request":false},{"name":"K.K. Lament","link":"https:\/\/animalcrossing.fandom.com\/wiki\/K.K._Lament","request":false},{"name":"K.K. Love Song","link":"https:\/\/animalcrossing.fandom.com\/wiki\/K.K._Love_Song","request":false},{"name":"K.K. Lullaby","link":"https:\/\/animalcrossing.fandom.com\/wiki\/K.K._Lullaby","request":false},{"name":"K.K. Mambo","link":"https:\/\/animalcrossing.fandom.com\/wiki\/K.K._Mambo","request":false},{"name":"K.K. Marathon","link":"https:\/\/animalcrossing.fandom.com\/wiki\/K.K._Marathon","request":false},{"name":"K.K. Mariachi (Changed the name from \"Se\u00f1or K.K.\")","link":"https:\/\/animalcrossing.fandom.com\/wiki\/Se%C3%B1or_K.K.","request":false},{"name":"K.K. March","link":"https:\/\/animalcrossing.fandom.com\/wiki\/K.K._March","request":false},{"name":"K.K. Metal","link":"https:\/\/animalcrossing.fandom.com\/wiki\/K.K._Metal","request":false},{"name":"K.K. Milonga","link":"https:\/\/animalcrossing.fandom.com\/wiki\/K.K._Milonga","request":false},{"name":"K.K. Moody","link":"https:\/\/animalcrossing.fandom.com\/wiki\/K.K._Moody","request":false},{"name":"K.K. Oasis","link":"https:\/\/animalcrossing.fandom.com\/wiki\/K.K._Oasis","request":false},{"name":"K.K. Parade","link":"https:\/\/animalcrossing.fandom.com\/wiki\/K.K._Parade","request":false},{"name":"K.K. Ragtime","link":"https:\/\/animalcrossing.fandom.com\/wiki\/K.K._Ragtime","request":false},{"name":"K.K. Rally","link":"https:\/\/animalcrossing.fandom.com\/wiki\/K.K._Rally","request":false},{"name":"K.K. Reggae","link":"https:\/\/animalcrossing.fandom.com\/wiki\/K.K._Reggae","request":false},{"name":"K.K. Rock","link":"https:\/\/animalcrossing.fandom.com\/wiki\/K.K._Rock","request":false},{"name":"K.K. Rockabilly","link":"https:\/\/animalcrossing.fandom.com\/wiki\/K.K._Rockabilly","request":false},{"name":"K.K. Safari","link":"https:\/\/animalcrossing.fandom.com\/wiki\/K.K._Safari","request":false},{"name":"K.K. Salsa","link":"https:\/\/animalcrossing.fandom.com\/wiki\/K.K._Salsa","request":false},{"name":"K.K. Samba","link":"https:\/\/animalcrossing.fandom.com\/wiki\/K.K._Samba","request":false},{"name":"K.K. Ska","link":"https:\/\/animalcrossing.fandom.com\/wiki\/K.K._Ska","request":false},{"name":"K.K. Sonata","link":"https:\/\/animalcrossing.fandom.com\/wiki\/K.K._Sonata","request":false},{"name":"K.K. Song","link":"https:\/\/animalcrossing.fandom.com\/wiki\/K.K._Song","request":false},{"name":"K.K. Soul","link":"https:\/\/animalcrossing.fandom.com\/wiki\/K.K._Soul","request":false},{"name":"K.K. Steppe","link":"https:\/\/animalcrossing.fandom.com\/wiki\/K.K._Steppe","request":false},{"name":"K.K. Stroll","link":"https:\/\/animalcrossing.fandom.com\/wiki\/K.K._Stroll","request":false},{"name":"K.K. Swing","link":"https:\/\/animalcrossing.fandom.com\/wiki\/K.K._Swing","request":false},{"name":"K.K. Synth","link":"https:\/\/animalcrossing.fandom.com\/wiki\/K.K._Synth","request":false},{"name":"K.K. Tango","link":"https:\/\/animalcrossing.fandom.com\/wiki\/K.K._Tango","request":false},{"name":"K.K. Technopop","link":"https:\/\/animalcrossing.fandom.com\/wiki\/K.K._Technopop","request":false},{"name":"K.K. Waltz","link":"https:\/\/animalcrossing.fandom.com\/wiki\/K.K._Waltz","request":false},{"name":"K.K. Western","link":"https:\/\/animalcrossing.fandom.com\/wiki\/K.K._Western","request":false},{"name":"King K.K.","link":"https:\/\/animalcrossing.fandom.com\/wiki\/King_K.K.","request":false},{"name":"Lucky K.K.","link":"https:\/\/animalcrossing.fandom.com\/wiki\/Lucky_K.K.","request":false},{"name":"Marine Song 2001","link":"https:\/\/animalcrossing.fandom.com\/wiki\/Marine_Song_2001","request":false},{"name":"Mountain Song","link":"https:\/\/animalcrossing.fandom.com\/wiki\/Mountain_Song","request":false},{"name":"Mr. K.K.","link":"https:\/\/animalcrossing.fandom.com\/wiki\/Mr._K.K.","request":false},{"name":"My Place","link":"https:\/\/animalcrossing.fandom.com\/wiki\/My_Place","request":false},{"name":"Neapolitan","link":"https:\/\/animalcrossing.fandom.com\/wiki\/Neapolitan","request":false},{"name":"Only Me","link":"https:\/\/animalcrossing.fandom.com\/wiki\/Only_Me","request":false},{"name":"Pondering","link":"https:\/\/animalcrossing.fandom.com\/wiki\/Pondering","request":false},{"name":"Rockin' K.K.","link":"https:\/\/animalcrossing.fandom.com\/wiki\/Rockin%27_K.K.","request":false},{"name":"Soulful K.K.","link":"https:\/\/animalcrossing.fandom.com\/wiki\/Soulful_K.K.","request":false},{"name":"Space K.K.","link":"https:\/\/animalcrossing.fandom.com\/wiki\/Space_K.K.","request":false},{"name":"Spring Blossoms","link":"https:\/\/animalcrossing.fandom.com\/wiki\/Spring_Blossoms","request":false},{"name":"Stale Cupcakes","link":"https:\/\/animalcrossing.fandom.com\/wiki\/Stale_Cupcakes","request":false},{"name":"Steep Hill","link":"https:\/\/animalcrossing.fandom.com\/wiki\/Steep_Hill","request":false},{"name":"Surfin' K.K.","link":"https:\/\/animalcrossing.fandom.com\/wiki\/Surfin%27_K.K.","request":false},{"name":"The K. Funk","link":"https:\/\/animalcrossing.fandom.com\/wiki\/The_K._Funk","request":false},{"name":"To the Edge","link":"https:\/\/animalcrossing.fandom.com\/wiki\/To_the_Edge","request":false},{"name":"Two Days Ago","link":"https:\/\/animalcrossing.fandom.com\/wiki\/Two_Days_Ago","request":false},{"name":"Wandering","link":"https:\/\/animalcrossing.fandom.com\/wiki\/Wandering","request":false},{"name":"Welcome Horizons","link":"https:\/\/animalcrossing.fandom.com\/wiki\/Welcome_Horizons","request":true}]